<?xml version="1.0" encoding="UTF-8" ?>
<!DOCTYPE mapper PUBLIC "-//mybatis.org//DTD Mapper 3.0//EN" "http://mybatis.org/dtd/mybatis-3-mapper.dtd" >
<mapper namespace="com.fangdeng.server.mapper.TagMapper" >
  <resultMap id="BaseResultMap" type="com.fangdeng.server.entity.Tag" >
    <!--
      WARNING - @mbggenerated
      This element is automatically generated by MyBatis Generator, do not modify.
      This element was generated on Tue Oct 12 18:31:38 CST 2021.
    -->
    <id column="id" property="id" jdbcType="INTEGER" />
    <result column="tag_name" property="tagName" jdbcType="VARCHAR" />
    <result column="create_time" property="createTime" jdbcType="TIMESTAMP" />
    <result column="update_time" property="updateTime" jdbcType="TIMESTAMP" />
    <result column="del_flag" property="delFlag" jdbcType="INTEGER" />
  </resultMap>
  <sql id="Base_Column_List" >
    <!--
      WARNING - @mbggenerated
      This element is automatically generated by MyBatis Generator, do not modify.
      This element was generated on Tue Oct 12 18:31:38 CST 2021.
    -->
    id, tag_name, create_time, update_time, del_flag
  </sql>
  <select id="selectByPrimaryKey" resultMap="BaseResultMap" parameterType="java.lang.Integer" >
    <!--
      WARNING - @mbggenerated
      This element is automatically generated by MyBatis Generator, do not modify.
      This element was generated on Tue Oct 12 18:31:38 CST 2021.
    -->
    select 
    <include refid="Base_Column_List" />
    from t_tag
    where id = #{id,jdbcType=INTEGER}
  </select>
  <delete id="deleteByPrimaryKey" parameterType="java.lang.Integer" >
    <!--
      WARNING - @mbggenerated
      This element is automatically generated by MyBatis Generator, do not modify.
      This element was generated on Tue Oct 12 18:31:38 CST 2021.
    -->
    delete from t_tag
    where id = #{id,jdbcType=INTEGER}
  </delete>
  <insert id="insert" parameterType="com.fangdeng.server.entity.Tag" >
    <!--
      WARNING - @mbggenerated
      This element is automatically generated by MyBatis Generator, do not modify.
      This element was generated on Tue Oct 12 18:31:38 CST 2021.
    -->
    insert into t_tag (id, tag_name, create_time, 
      update_time, del_flag)
    values (#{id,jdbcType=INTEGER}, #{tagName,jdbcType=VARCHAR}, #{createTime,jdbcType=TIMESTAMP}, 
      #{updateTime,jdbcType=TIMESTAMP}, #{delFlag,jdbcType=INTEGER})
  </insert>
  <insert id="insertSelective" parameterType="com.fangdeng.server.entity.Tag" >
    <!--
      WARNING - @mbggenerated
      This element is automatically generated by MyBatis Generator, do not modify.
      This element was generated on Tue Oct 12 18:31:38 CST 2021.
    -->
    insert into t_tag
    <trim prefix="(" suffix=")" suffixOverrides="," >
      <if test="id != null" >
        id,
      </if>
      <if test="tagName != null" >
        tag_name,
      </if>
      <if test="createTime != null" >
        create_time,
      </if>
      <if test="updateTime != null" >
        update_time,
      </if>
      <if test="delFlag != null" >
        del_flag,
      </if>
    </trim>
    <trim prefix="values (" suffix=")" suffixOverrides="," >
      <if test="id != null" >
        #{id,jdbcType=INTEGER},
      </if>
      <if test="tagName != null" >
        #{tagName,jdbcType=VARCHAR},
      </if>
      <if test="createTime != null" >
        #{createTime,jdbcType=TIMESTAMP},
      </if>
      <if test="updateTime != null" >
        #{updateTime,jdbcType=TIMESTAMP},
      </if>
      <if test="delFlag != null" >
        #{delFlag,jdbcType=INTEGER},
      </if>
    </trim>
  </insert>
  <update id="updateByPrimaryKeySelective" parameterType="com.fangdeng.server.entity.Tag" >
    <!--
      WARNING - @mbggenerated
      This element is automatically generated by MyBatis Generator, do not modify.
      This element was generated on Tue Oct 12 18:31:38 CST 2021.
    -->
    update t_tag
    <set >
      <if test="tagName != null" >
        tag_name = #{tagName,jdbcType=VARCHAR},
      </if>
      <if test="createTime != null" >
        create_time = #{createTime,jdbcType=TIMESTAMP},
      </if>
      <if test="updateTime != null" >
        update_time = #{updateTime,jdbcType=TIMESTAMP},
      </if>
      <if test="delFlag != null" >
        del_flag = #{delFlag,jdbcType=INTEGER},
      </if>
    </set>
    where id = #{id,jdbcType=INTEGER}
  </update>
  <update id="updateByPrimaryKey" parameterType="com.fangdeng.server.entity.Tag" >
    <!--
      WARNING - @mbggenerated
      This element is automatically generated by MyBatis Generator, do not modify.
      This element was generated on Tue Oct 12 18:31:38 CST 2021.
    -->
    update t_tag
    set tag_name = #{tagName,jdbcType=VARCHAR},
      create_time = #{createTime,jdbcType=TIMESTAMP},
      update_time = #{updateTime,jdbcType=TIMESTAMP},
      del_flag = #{delFlag,jdbcType=INTEGER}
    where id = #{id,jdbcType=INTEGER}
  </update>
  <insert id="batchInsert">
    insert into t_tag (tag_name, create_time,
    update_time, del_flag) values
    <foreach collection="list" separator="," item="item" index="index">
      ( #{item}, now(),now() ,0
      )
    </foreach>
  </insert>
  <select id="list" resultType="com.fangdeng.server.entity.Tag">
    select
    <include refid="Base_Column_List"/>
    from t_tag
    where del_flag =0
  </select>
  <select id="listTagName" resultType="java.lang.String">
    select distinct tag_name
    from t_tag
    where del_flag =0
  </select>
</mapper>